fiftyone/__init__.py
fiftyone/__public__.py
fiftyone/constants.py
fiftyone/core/__init__.py
fiftyone/core/aggregations.py
fiftyone/core/annotation.py
fiftyone/core/brain.py
fiftyone/core/cli.py
fiftyone/core/clips.py
fiftyone/core/collections.py
fiftyone/core/config.py
fiftyone/core/context.py
fiftyone/core/dataset.py
fiftyone/core/document.py
fiftyone/core/evaluation.py
fiftyone/core/expressions.py
fiftyone/core/fields.py
fiftyone/core/frame.py
fiftyone/core/frame_utils.py
fiftyone/core/groups.py
fiftyone/core/json.py
fiftyone/core/labels.py
fiftyone/core/logging.py
fiftyone/core/media.py
fiftyone/core/metadata.py
fiftyone/core/models.py
fiftyone/core/patches.py
fiftyone/core/runs.py
fiftyone/core/sample.py
fiftyone/core/service.py
fiftyone/core/singletons.py
fiftyone/core/stages.py
fiftyone/core/state.py
fiftyone/core/storage.py
fiftyone/core/uid.py
fiftyone/core/utils.py
fiftyone/core/validation.py
fiftyone/core/video.py
fiftyone/core/view.py
fiftyone/core/map/__init__.py
fiftyone/core/map/factory.py
fiftyone/core/map/mapper.py
fiftyone/core/map/process.py
fiftyone/core/map/threading.py
fiftyone/core/map/typing.py
fiftyone/core/map/batcher/__init__.py
fiftyone/core/map/batcher/batch.py
fiftyone/core/map/batcher/id_batch.py
fiftyone/core/map/batcher/slice_batch.py
fiftyone/core/odm/__init__.py
fiftyone/core/odm/database.py
fiftyone/core/odm/dataset.py
fiftyone/core/odm/document.py
fiftyone/core/odm/embedded_document.py
fiftyone/core/odm/frame.py
fiftyone/core/odm/mixins.py
fiftyone/core/odm/runs.py
fiftyone/core/odm/sample.py
fiftyone/core/odm/utils.py
fiftyone/core/odm/views.py
fiftyone/core/odm/workspace.py
fiftyone/core/plots/__init__.py
fiftyone/core/plots/base.py
fiftyone/core/plots/manager.py
fiftyone/core/plots/matplotlib.py
fiftyone/core/plots/plotly.py
fiftyone/core/plots/utils.py
fiftyone/core/plots/views.py
fiftyone/core/session/__init__.py
fiftyone/core/session/client.py
fiftyone/core/session/events.py
fiftyone/core/session/notebooks.py
fiftyone-1.11.0.dist-info/licenses/LICENSE
fiftyone-1.11.0.dist-info/METADATA
fiftyone-1.11.0.dist-info/WHEEL
fiftyone-1.11.0.dist-info/entry_points.txt
fiftyone-1.11.0.dist-info/top_level.txt
fiftyone-1.11.0.dist-info/RECORD
