Metadata-Version: 2.4
Name: fiftyone
Version: 1.11.0
Summary: FiftyOne: the open-source tool for building high-quality datasets and computer vision models
Home-page: https://github.com/voxel51/fiftyone
Author: Voxel51, Inc.
Author-email: info@voxel51.com
License: Apache
Classifier: Development Status :: 5 - Production/Stable
Classifier: Intended Audience :: Developers
Classifier: Intended Audience :: Science/Research
Classifier: License :: OSI Approved :: Apache Software License
Classifier: Topic :: Scientific/Engineering :: Artificial Intelligence
Classifier: Topic :: Scientific/Engineering :: Image Processing
Classifier: Topic :: Scientific/Engineering :: Image Recognition
Classifier: Topic :: Scientific/Engineering :: Information Analysis
Classifier: Topic :: Scientific/Engineering :: Visualization
Classifier: Operating System :: MacOS :: MacOS X
Classifier: Operating System :: POSIX :: Linux
Classifier: Operating System :: Microsoft :: Windows
Classifier: Programming Language :: Python :: 3
Classifier: Programming Language :: Python :: 3.9
Classifier: Programming Language :: Python :: 3.10
Classifier: Programming Language :: Python :: 3.11
Classifier: Programming Language :: Python :: 3.12
Requires-Python: >=3.9
License-File: LICENSE
Requires-Dist: aiofiles
Requires-Dist: argcomplete
Requires-Dist: async_lru>=2
Requires-Dist: beautifulsoup4
Requires-Dist: boto3
Requires-Dist: cachetools
Requires-Dist: dacite<2,>=1.6.0
Requires-Dist: dill
Requires-Dist: Deprecated
Requires-Dist: ftfy
Requires-Dist: humanize
Requires-Dist: hypercorn>=0.13.2
Requires-Dist: Jinja2>=3
Requires-Dist: jsonpatch
Requires-Dist: matplotlib
Requires-Dist: mongoengine~=0.29.1
Requires-Dist: motor~=3.6.0
Requires-Dist: numpy
Requires-Dist: packaging
Requires-Dist: pandas
Requires-Dist: Pillow!=11.2.*,>=6.2
Requires-Dist: plotly>=6.1.1
Requires-Dist: pprintpp
Requires-Dist: psutil
Requires-Dist: pymongo~=4.9.2
Requires-Dist: pytz
Requires-Dist: PyYAML
Requires-Dist: regex
Requires-Dist: retrying
Requires-Dist: rtree
Requires-Dist: scikit-learn
Requires-Dist: scikit-image
Requires-Dist: scipy
Requires-Dist: setuptools
Requires-Dist: sseclient-py<2,>=1.7.2
Requires-Dist: sse-starlette<1,>=0.10.3
Requires-Dist: starlette>=0.24.0
Requires-Dist: strawberry-graphql>=0.262.4
Requires-Dist: tabulate
Requires-Dist: tqdm
Requires-Dist: xmltodict
Requires-Dist: universal-analytics-python3<2,>=1.0.1
Requires-Dist: pydash
Requires-Dist: fiftyone-brain<0.22,>=0.21.4
Requires-Dist: fiftyone-db<2.0,>=0.4
Requires-Dist: voxel51-eta<0.16,>=0.15.1
Requires-Dist: opencv-python-headless
Dynamic: author
Dynamic: author-email
Dynamic: classifier
Dynamic: description
Dynamic: description-content-type
Dynamic: home-page
Dynamic: license
Dynamic: license-file
Dynamic: requires-dist
Dynamic: requires-python
Dynamic: summary
